MANIFEST.in
README.md
requirements.txt
setup.py
test_requirements.txt
version.txt
cloudshell/__init__.py
cloudshell/networking/__init__.py
cloudshell/networking/huawei/__init__.py
cloudshell/networking/huawei/autoload/__init__.py
cloudshell/networking/huawei/autoload/huawei_snmp_autoload.py
cloudshell/networking/huawei/autoload/snmp_entity_table.py
cloudshell/networking/huawei/autoload/snmp_if_entity.py
cloudshell/networking/huawei/autoload/snmp_if_port_channel_entity.py
cloudshell/networking/huawei/autoload/snmp_if_port_entity.py
cloudshell/networking/huawei/autoload/snmp_if_table.py
cloudshell/networking/huawei/autoload/snmp_port_attr_tables.py
cloudshell/networking/huawei/cli/__init__.py
cloudshell/networking/huawei/cli/huawei_cli_handler.py
cloudshell/networking/huawei/cli/huawei_command_modes.py
cloudshell/networking/huawei/command_actions/__init__.py
cloudshell/networking/huawei/command_actions/add_remove_vlan_actions.py
cloudshell/networking/huawei/command_actions/enable_disable_snmp_actions.py
cloudshell/networking/huawei/command_actions/firmware_actions.py
cloudshell/networking/huawei/command_actions/save_restore_actions.py
cloudshell/networking/huawei/command_actions/system_actions.py
cloudshell/networking/huawei/command_templates/__init__.py
cloudshell/networking/huawei/command_templates/add_remove_vlan.py
cloudshell/networking/huawei/command_templates/configuration.py
cloudshell/networking/huawei/command_templates/enable_disable_snmp.py
cloudshell/networking/huawei/command_templates/firmware.py
cloudshell/networking/huawei/command_templates/system.py
cloudshell/networking/huawei/flows/__init__.py
cloudshell/networking/huawei/flows/huawei_add_vlan_flow.py
cloudshell/networking/huawei/flows/huawei_autoload_flow.py
cloudshell/networking/huawei/flows/huawei_disable_snmp_flow.py
cloudshell/networking/huawei/flows/huawei_enable_snmp_flow.py
cloudshell/networking/huawei/flows/huawei_file_system_flow.py
cloudshell_networking_huawei.egg-info/PKG-INFO
cloudshell_networking_huawei.egg-info/SOURCES.txt
cloudshell_networking_huawei.egg-info/dependency_links.txt
cloudshell_networking_huawei.egg-info/requires.txt
cloudshell_networking_huawei.egg-info/top_level.txt
