Metadata-Version: 1.0
Name: cloudshell-networking-huawei
Version: 3.0.4
Summary: QualiSystems networking Huawei specific package
Home-page: http://www.qualisystems.com/
Author: QualiSystems
Author-email: info@qualisystems.com
License: UNKNOWN
Platform: UNKNOWN
